{
    "carts": [
        {
            "id": 1,
            "user_id": 1,
            "cart_shops": [
                {
                    "id": 1,
                    "shop": {
                        "id": 5,
                        "shop_name": "Shop A"
                    },
                    "cart_items": [
                        {
                            "id": 1,
                            "product_variant": {
                                "id": 1,
                                "product": {
                                    "id": 2,
                                    "product_name": "Áo thun đỏ"
                                },
                                "image_url": "product_variants/1729823829-áo thun đỏ.jpg",
                                "unit_price": 200000
                            },
                            "quantity": 2
                        },
                        {
                            "id": 2,
                            "product_variant": {
                                "id": 3,
                                "product": {
                                    "id": 4,
                                    "product_name": "Quần jean xanh"
                                },
                                "image_url": "product_variants/1729823830-quần jean xanh.jpg",
                                "unit_price": 350000
                            },
                            "quantity": 1
                        }
                    ]
                },
                {
                    "id": 2,
                    "shop": {
                        "id": 6,
                        "shop_name": "Shop B"
                    },
                    "cart_items": [
                        {
                            "id": 3,
                            "product_variant": {
                                "id": 5,
                                "product": {
                                    "id": 6,
                                    "product_name": "Giày sneaker"
                                },
                                "image_url": "product_variants/1729823841-giày sneaker.jpg",
                                "unit_price": 800000
                            },
                            "quantity": 1
                        }
                    ]
                }
            ]
        }
    ]
}